cool_seq_tool/__init__.py
cool_seq_tool/app.py
cool_seq_tool/schemas.py
cool_seq_tool/utils.py
cool_seq_tool/handlers/__init__.py
cool_seq_tool/handlers/seqrepo_access.py
cool_seq_tool/mappers/__init__.py
cool_seq_tool/mappers/alignment.py
cool_seq_tool/mappers/exon_genomic_coords.py
cool_seq_tool/mappers/feature_overlap.py
cool_seq_tool/mappers/liftover.py
cool_seq_tool/mappers/mane_transcript.py
cool_seq_tool/resources/__init__.py
cool_seq_tool/resources/data_files.py
cool_seq_tool/resources/status.py
cool_seq_tool/resources/transcript_mapping.tsv
cool_seq_tool/sources/__init__.py
cool_seq_tool/sources/mane_transcript_mappings.py
cool_seq_tool/sources/transcript_mappings.py
cool_seq_tool/sources/uta_database.py
cool_seq_tool-0.15.3.dist-info/licenses/LICENSE
cool_seq_tool-0.15.3.dist-info/METADATA
cool_seq_tool-0.15.3.dist-info/WHEEL
cool_seq_tool-0.15.3.dist-info/top_level.txt
cool_seq_tool-0.15.3.dist-info/RECORD
