Metadata-Version: 2.4
Name: cool_seq_tool
Version: 0.15.3
Summary: Common Operation on Lots of Sequences Tool
Author: Kori Kuzma, James Stevenson, Katie Stahl, Alex Wagner
License-Expression: MIT
Project-URL: Homepage, https://github.com/genomicmedlab/cool-seq-tool
Project-URL: Documentation, https://coolseqtool.readthedocs.io/
Project-URL: Changelog, https://github.com/genomicmedlab/cool-seq-tool/releases
Project-URL: Source, https://github.com/genomicmedlab/cool-seq-tool
Project-URL: Bug Tracker, https://github.com/genomicmedlab/cool-seq-tool/issues
Classifier: Development Status :: 3 - Alpha
Classifier: Framework :: Pydantic
Classifier: Framework :: Pydantic :: 2
Classifier: Intended Audience :: Science/Research
Classifier: Intended Audience :: Developers
Classifier: Topic :: Scientific/Engineering :: Bio-Informatics
Classifier: Programming Language :: Python :: 3
Classifier: Programming Language :: Python :: 3.11
Classifier: Programming Language :: Python :: 3.12
Classifier: Programming Language :: Python :: 3.13
Requires-Python: >=3.11
License-File: LICENSE
Requires-Dist: asyncpg
Requires-Dist: boto3
Requires-Dist: agct>=0.2.0rc1
Requires-Dist: polars~=1.0
Requires-Dist: biocommons.seqrepo
Requires-Dist: pydantic<3.0,>=2.0
Requires-Dist: ga4gh.vrs<3.0,>=2.2.0
Requires-Dist: wags-tails~=0.4.0
Requires-Dist: bioutils
Provides-Extra: dev
Requires-Dist: prek>=0.2.23; extra == "dev"
Requires-Dist: ipython; extra == "dev"
Requires-Dist: ipykernel; extra == "dev"
Requires-Dist: psycopg2-binary; extra == "dev"
Requires-Dist: ruff==0.14.10; extra == "dev"
Provides-Extra: tests
Requires-Dist: pytest; extra == "tests"
Requires-Dist: pytest-cov; extra == "tests"
Requires-Dist: pytest-asyncio; extra == "tests"
Requires-Dist: mock; extra == "tests"
Provides-Extra: docs
Requires-Dist: sphinx==6.1.3; extra == "docs"
Requires-Dist: sphinx-autodoc-typehints==1.22.0; extra == "docs"
Requires-Dist: sphinx-autobuild==2021.3.14; extra == "docs"
Requires-Dist: sphinx-copybutton==0.5.2; extra == "docs"
Requires-Dist: sphinxext-opengraph==0.8.2; extra == "docs"
Requires-Dist: furo==2023.3.27; extra == "docs"
Requires-Dist: sphinx-github-changelog==1.2.1; extra == "docs"
Dynamic: license-file
